gradle.properties
hexdoc_oneironaut/__gradle_version__.py
hexdoc_oneironaut/__init__.py
hexdoc_oneironaut/__version__.py
hexdoc_oneironaut/_hooks.py
hexdoc_oneironaut/py.typed
hexdoc_oneironaut/_export/.gitignore
hexdoc_oneironaut/_export/__init__.py
hexdoc_oneironaut/_export/generated/__init__.py
hexdoc_oneironaut/_export/generated/oneironaut.hexdoc.json
hexdoc_oneironaut/_export/generated/oneironaut.patterns.hexdoc.json
hexdoc_oneironaut/_export/generated/assets/hexcasting/lang/en_us.flatten.json5
hexdoc_oneironaut/_export/generated/assets/oneironaut/lang/en_us.json
hexdoc_oneironaut/_export/generated/assets/oneironaut/lang/zh_cn.json
hexdoc_oneironaut/_export/generated/assets/oneironaut/models/block/cell.json
hexdoc_oneironaut/_export/generated/assets/oneironaut/models/block/circle.json
hexdoc_oneironaut/_export/generated/assets/oneironaut/models/block/hex_resistant_block.json
hexdoc_oneironaut/_export/generated/assets/oneironaut/models/block/hover_elevator_unpowered.json
hexdoc_oneironaut/_export/generated/assets/oneironaut/models/block/hover_repeater.json
hexdoc_oneironaut/_export/generated/assets/oneironaut/models/block/media_gel.json
hexdoc_oneironaut/_export/generated/assets/oneironaut/models/block/media_ice.json
hexdoc_oneironaut/_export/generated/assets/oneironaut/models/block/noosphere_basalt.json
hexdoc_oneironaut/_export/generated/assets/oneironaut/models/block/pseudoamethyst_block.json
hexdoc_oneironaut/_export/generated/assets/oneironaut/models/block/raycast_blocker.json
hexdoc_oneironaut/_export/generated/assets/oneironaut/models/block/raycast_blocker_glass.json
hexdoc_oneironaut/_export/generated/assets/oneironaut/models/block/sentinel_sensor.json
hexdoc_oneironaut/_export/generated/assets/oneironaut/models/block/sentinel_trap_powered.json
hexdoc_oneironaut/_export/generated/assets/oneironaut/models/block/super_budding.json
hexdoc_oneironaut/_export/generated/assets/oneironaut/models/block/wisp_battery_decorative_off.json
hexdoc_oneironaut-0.4.0.1.0.dist-info/METADATA
hexdoc_oneironaut-0.4.0.1.0.dist-info/WHEEL
hexdoc_oneironaut-0.4.0.1.0.dist-info/entry_points.txt
hexdoc_oneironaut-0.4.0.1.0.dist-info/licenses/LICENSE
hexdoc_oneironaut-0.4.0.1.0.dist-info/RECORD
