Metadata-Version: 2.4
Name: hexdoc-oneironaut
Version: 0.4.0.1.0
Summary: Python web book docgen and hexdoc plugin for Oneironaut.
Project-URL: Homepage, https://beholderface.github.io/oneironaut
Project-URL: Source, https://github.com/beholderface/oneironaut
Author: beholderface
License-File: LICENSE
Keywords: hexdoc
Requires-Python: >=3.11
Requires-Dist: hexdoc-hexcasting~=0.10.3.1.0.dev22
Provides-Extra: dev
Requires-Dist: ruff~=0.1.4; extra == 'dev'
